proxy.py
py_proxy-0.2.6.dist-info/LICENSE
py_proxy-0.2.6.dist-info/METADATA
py_proxy-0.2.6.dist-info/WHEEL
py_proxy-0.2.6.dist-info/top_level.txt
py_proxy-0.2.6.dist-info/RECORD
