Metadata-Version: 2.1
Name: py-proxy
Version: 0.2.6
Summary: A proxy library for python 3
Home-page: https://github.com/HOWZ1T/py_proxy
Author: HOWZ1T
Author-email: dylan.d.randall@gmail.com
License: MIT License
Project-URL: Bug Reports, https://github.com/HOWZ1T/py_proxy/issues
Project-URL: Source, https://github.com/HOWZ1T/py_proxy
Platform: UNKNOWN
Classifier: Programming Language :: Python :: 3
Classifier: Programming Language :: Python :: 3.4
Classifier: Programming Language :: Python :: 3.5
Classifier: Programming Language :: Python :: 3.6
Classifier: Programming Language :: Python :: 3.7
Classifier: License :: OSI Approved :: MIT License
Classifier: Operating System :: OS Independent
Classifier: Development Status :: 4 - Beta
Classifier: Intended Audience :: Developers
Classifier: Topic :: Internet :: Proxy Servers
Requires-Dist: requests
Requires-Dist: beautifulsoup4
